{
	"pools": [
		{
			"rolls": {
				"min": 1,
				"max": 5
			},
			"bonus_rolls": {
				"min": 1.7,
				"max": 5.7
			},
			"entries": [
				{
					"type": "item",
					"name": "backrooms:raw_almond_water",
					"weight": 2,
					"functions": [
						{
							"function": "set_count",
							"count": {
								"min": 1,
								"max": 2
							}
						}
					]
				},
				{
					"type": "item",
					"name": "backrooms:almond_water",
					"weight": 1,
					"functions": [
						{
							"function": "set_count",
							"count": {
								"min": 1,
								"max": 1
							}
						}
					]
				},
				{
					"type": "item",
					"name": "backrooms:music_disc_its_been_so_long",
					"weight": 1
				},
				{
					"type": "item",
					"name": "backrooms:music_disc_burgers_and_fries",
					"weight": 1
				},
				{
					"type": "item",
					"name": "backrooms:music_disc_012",
					"weight": 1
				},
				{
					"type": "item",
					"name": "minecraft:golden_apple",
					"weight": 1,
					"functions": [
						{
							"function": "set_count",
							"count": {
								"min": 1,
								"max": 2
							}
						}
					]
				},
				{
					"type": "item",
					"name": "minecraft:string",
					"weight": 20,
					"functions": [
						{
							"function": "set_count",
							"count": {
								"min": 1,
								"max": 8
							}
						}
					]
				},
				{
					"type": "item",
					"name": "minecraft:rotten_flesh",
					"weight": 20,
					"functions": [
						{
							"function": "set_count",
							"count": {
								"min": 1,
								"max": 17
							}
						}
					]
				}
			]
		}
	]
}
